<?xml version="1.0" encoding="UTF-8"?>
<!DOCTYPE mapper PUBLIC "-//mybatis.org//DTD Mapper 3.0//EN" "http://mybatis.org/dtd/mybatis-3-mapper.dtd">
<mapper namespace="kr.co.infovine.dkmm.mapper.admin.TAdminProgramMapper">
  <resultMap id="BaseResultMap" type="kr.co.infovine.dkmm.db.model.admin.TbAdminProgramModel">
    <!--
      WARNING - @mbg.generated
      This element is automatically generated by MyBatis Generator, do not modify.
      This element was generated on Mon May 10 14:15:22 KST 2021.
    -->
    <id column="admin_program_seq" jdbcType="INTEGER" property="adminProgramSeq" />
    <result column="program_id" jdbcType="VARCHAR" property="programId" />
    <result column="parents_program_id" jdbcType="VARCHAR" property="parentsProgramId" />
    <result column="level" jdbcType="VARCHAR" property="level" />
    <result column="program_name" jdbcType="VARCHAR" property="programName" />
    <result column="program_sort" jdbcType="VARCHAR" property="programSort" />
    <result column="use_yn" jdbcType="VARCHAR" property="useYn" />
    <result column="reg_date" jdbcType="VARCHAR" property="regDate" />
    <result column="update_date" jdbcType="VARCHAR" property="updateDate" />
    <result column="location" jdbcType="LONGVARCHAR" property="location" />
  </resultMap>
  <delete id="deleteByPrimaryKey" parameterType="java.lang.Integer">
    <!--
      WARNING - @mbg.generated
      This element is automatically generated by MyBatis Generator, do not modify.
      This element was generated on Mon May 10 14:15:22 KST 2021.
    -->
    delete from t_admin_program
    where admin_program_seq = #{adminProgramSeq,jdbcType=INTEGER}
  </delete>
  <insert id="insert" parameterType="kr.co.infovine.dkmm.db.model.admin.TbAdminProgramModel">
    <!--
      WARNING - @mbg.generated
      This element is automatically generated by MyBatis Generator, do not modify.
      This element was generated on Mon May 10 14:15:22 KST 2021.
    -->
    insert into t_admin_program (program_id, parents_program_id, 
      level, program_name, program_sort, 
      use_yn, reg_date, update_date, 
      location)
    values (#{programId,jdbcType=VARCHAR}, #{parentsProgramId,jdbcType=VARCHAR}, 
      #{level,jdbcType=VARCHAR}, #{programName,jdbcType=VARCHAR}, #{programSort,jdbcType=VARCHAR}, 
     #{useYn,jdbcType=VARCHAR}, #{regDate,jdbcType=VARCHAR}, #{updateDate,jdbcType=VARCHAR}, 
      #{location,jdbcType=LONGVARCHAR})
  </insert>
  <update id="updateByPrimaryKey" parameterType="kr.co.infovine.dkmm.db.model.admin.TbAdminProgramModel">
    <!--
      WARNING - @mbg.generated
      This element is automatically generated by MyBatis Generator, do not modify.
      This element was generated on Mon May 10 14:15:22 KST 2021.
    -->
    update t_admin_program
    set program_id = #{programId,jdbcType=VARCHAR},
      parents_program_id = #{parentsProgramId,jdbcType=VARCHAR},
      level = #{level,jdbcType=VARCHAR},
      program_name = #{programName,jdbcType=VARCHAR},
      program_sort = #{programSort,jdbcType=VARCHAR},
      use_yn = #{useYn,jdbcType=VARCHAR},
      <if test="regDate != null">
        reg_date = #{regDate,jdbcType=VARCHAR},
      </if>
      <if test="updateDate != null">
      update_date = #{updateDate,jdbcType=VARCHAR},
      </if>
      location = #{location,jdbcType=LONGVARCHAR}
    where admin_program_seq = #{adminProgramSeq,jdbcType=INTEGER}
  </update>
  <select id="selectByPrimaryKey" parameterType="java.lang.Integer" resultMap="BaseResultMap">
    <!--
      WARNING - @mbg.generated
      This element is automatically generated by MyBatis Generator, do not modify.
      This element was generated on Mon May 10 14:15:22 KST 2021.
    -->
    select admin_program_seq, program_id, parents_program_id, level, program_name, program_sort, 
    use_yn, location
    ,reg_date
    ,update_date 
    from t_admin_program
    where admin_program_seq = #{adminProgramSeq,jdbcType=INTEGER}
    <![CDATA[
    and use_yn<>'N'
    ]]>
  </select>
  
  <select id="selectAll" resultMap="BaseResultMap">
    <!--
      WARNING - @mbg.generated
      This element is automatically generated by MyBatis Generator, do not modify.
      This element was generated on Mon May 10 14:15:22 KST 2021.
    -->
    select admin_program_seq, program_id, parents_program_id, level, program_name, program_sort, 
    use_yn, location
    ,reg_date
    ,update_date 
    from t_admin_program
    where 1=1
    <if test='searchStartDt neq null and !"".equals(searchStartDt)'>
      AND substring(reg_date, 0, 5)||'-'||substring(reg_date, 5, 2)||'-'||substring(reg_date, 7, 2) BETWEEN #{searchStartDt} AND #{searchEndDt}
    </if>
    <if test='searchText neq null and !"".equals(searchText)'>
      AND program_name LIKE CONCAT('%', #{searchText}, '%')
    </if>
    <if test='searchLevel neq null and !"".equals(searchLevel)'>
      AND level = #{searchLevel}
    </if>
    order by program_sort desc, program_id asc
  </select>
  
  <select id="selectNextProgramId" resultMap="BaseResultMap">
    select MAX(CAST (program_id AS integer) ) + 1 as program_id
    from t_admin_program
    where 1=1
    and (program_id = #{programId} OR parents_program_id = #{programId})
  </select>
  
</mapper>